LICENSE
MANIFEST.in
README.rst
lgpl-2.1.txt
setup.py
pkgwat/__init__.py
pkgwat.cli.egg-info/PKG-INFO
pkgwat.cli.egg-info/SOURCES.txt
pkgwat.cli.egg-info/dependency_links.txt
pkgwat.cli.egg-info/entry_points.txt
pkgwat.cli.egg-info/namespace_packages.txt
pkgwat.cli.egg-info/not-zip-safe
pkgwat.cli.egg-info/requires.txt
pkgwat.cli.egg-info/top_level.txt
pkgwat/cli/__init__.py
pkgwat/cli/main.py
pkgwat/cli/subcommands.py
pkgwat/cli/utils.py
tests/test_utils.py
tests/__pycache__/test_utils.cpython-27-PYTEST.pyc
tests/__pycache__/test_utils.cpython-36-PYTEST.pyc