Metadata-Version: 1.1
Name: pkgwat.cli
Version: 0.13
Summary: CLI tool for querying the fedora packages webapp
Home-page: http://github.com/fedora-infra/pkgwat.cli
Author: Ralph Bean
Author-email: rbean@redhat.com
License: LGPLv2+
Platform: UNKNOWN
Classifier: License :: OSI Approved :: GNU Lesser General Public License v2 or later (LGPLv2+)
Classifier: Programming Language :: Python :: 2
Classifier: Programming Language :: Python :: 2.7
Classifier: Programming Language :: Python :: 3
Classifier: Programming Language :: Python :: 3.2
Classifier: Topic :: System :: Archiving :: Packaging
Classifier: Development Status :: 4 - Beta
